{
    "boxShadow": "none",
    "mobileBottomRow": 102,
    "widgetName": "AudioRecorder1",
    "displayName": "Audio Recorder",
    "iconSVG": "/static/media/icon.6854d49465b2ead1c3155f6916b01d0d.svg",
    "searchTags": [
        "sound recorder",
        "voice recorder"
    ],
    "topRow": 95,
    "bottomRow": 102,
    "parentRowSpace": 10,
    "type": "AUDIO_RECORDER_WIDGET",
    "hideCard": false,
    "mobileRightColumn": 61,
    "topRowBeforeCollapse": 95,
    "animateLoading": true,
    "parentColumnSpace": 12.578125,
    "leftColumn": 62,
    "dynamicBindingPathList": [
        {"key": "accentColor"},
        {"key": "borderRadius"}
    ],
    "isDisabled": false,
    "key": "txsjznv8sc",
    "isDeprecated": false,
    "rightColumn": 64,
    "widgetId": "7iffbfhelo",
    "accentColor": "{{appsmith.theme.colors.primaryColor}}",
    "bottomRowBeforeCollapse": 102,
    "minWidth": 450,
    "isVisible": true,
    "version": 1,
    "parentId": "0",
    "renderMode": "CANVAS",
    "isLoading": false,
    "mobileTopRow": 95,
    "responsiveBehavior": "fill",
    "originalTopRow": 95,
    "borderRadius": "{{appsmith.theme.borderRadius.appBorderRadius}}",
    "mobileLeftColumn": 45,
    "originalBottomRow": 102,
    "iconColor": "white"
}