{
    "boxShadow": "{{appsmith.theme.boxShadow.appBoxShadow}}",
    "multiRowSelection": false,
    "borderColor": "#E0DEDE",
    "onSort": "{{\n            Find_query1.run();\n            Total_record_query1.run();\n          }}",
    "isVisibleDownload": true,
    "iconSVG": "/static/media/icon.24905525921dd6f5ff46d0dd843b9e12.svg",
    "topRow": 11,
    "isSortable": true,
    "onPageChange": "{{\n            Find_query1.run();\n            Total_record_query1.run();\n          }}",
    "type": "TABLE_WIDGET_V2",
    "inlineEditingSaveOption": "CUSTOM",
    "animateLoading": true,
    "dynamicBindingPathList": [
        {"key": "accentColor"},
        {"key": "borderRadius"},
        {"key": "boxShadow"},
        {"key": "totalRecordsCount"},
        {"key": "primaryColumns.id.computedValue"},
        {"key": "primaryColumns.brand.computedValue"}
    ],
    "needsHeightForContent": true,
    "leftColumn": 2,
    "delimiter": ",",
    "defaultSelectedRowIndex": "9",
    "showInlineEditingOptionDropdown": true,
    "accentColor": "{{appsmith.theme.colors.primaryColor}}",
    "isVisibleFilters": true,
    "isVisible": true,
    "enableClientSideSearch": false,
    "version": 2,
    "totalRecordsCount": "{{Total_record_query1.data.n}}",
    "isLoading": false,
    "onSearchTextChanged": "{{\n            Find_query1.run();\n            Total_record_query1.run();\n          }}",
    "childStylesheet": {
        "button": {
            "boxShadow": "none",
            "borderRadius": "{{appsmith.theme.borderRadius.appBorderRadius}}",
            "buttonColor": "{{appsmith.theme.colors.primaryColor}}"
        },
        "iconButton": {
            "boxShadow": "none",
            "borderRadius": "{{appsmith.theme.borderRadius.appBorderRadius}}",
            "buttonColor": "{{appsmith.theme.colors.primaryColor}}"
        },
        "menuButton": {
            "boxShadow": "none",
            "borderRadius": "{{appsmith.theme.borderRadius.appBorderRadius}}",
            "menuColor": "{{appsmith.theme.colors.primaryColor}}"
        },
        "editActions": {
            "saveButtonColor": "{{appsmith.theme.colors.primaryColor}}",
            "saveBorderRadius": "{{appsmith.theme.borderRadius.appBorderRadius}}",
            "discardBorderRadius": "{{appsmith.theme.borderRadius.appBorderRadius}}",
            "discardButtonColor": "{{appsmith.theme.colors.primaryColor}}"
        }
    },
    "borderRadius": "{{appsmith.theme.borderRadius.appBorderRadius}}",
    "columnUpdatedAt": 1687158699215,
    "defaultSelectedRowIndices": "",
    "mobileBottomRow": 39,
    "widgetName": "Table1",
    "defaultPageSize": 0,
    "columnOrder": [
        "id",
        "brand"
    ],
    "dynamicPropertyPathList": [{"key": "tableData"}],
    "displayName": "Table",
    "bottomRow": 50,
    "columnWidthMap": {},
    "parentRowSpace": 10,
    "hideCard": false,
    "onAddNewRowSave": "{{Insert_query1.run(() => {\n            showAlert(\"Successfully created!\");\n            Find_query1.run()\n          }, () => {\n            showAlert(\"Unable to create!\");\n          })}}",
    "mobileRightColumn": 39,
    "parentColumnSpace": 12.578125,
    "dynamicTriggerPathList": [
        {"key": "onPageChange"},
        {"key": "onSearchTextChanged"},
        {"key": "onSort"},
        {"key": "onAddNewRowSave"}
    ],
    "borderWidth": "1",
    "primaryColumns": {
        "id": {
            "computedValue": "{{Table1.processedTableData.map((currentRow, currentIndex) => ( currentRow[\"id\"]))}}",
            "isEditable": false,
            "alias": "id",
            "enableSort": true,
            "isSaveVisible": true,
            "id": "id",
            "isDisabled": false,
            "allowSameOptionsInNewRow": true,
            "validation": {},
            "isCellVisible": true,
            "isDerived": false,
            "textSize": "0.875rem",
            "allowCellWrapping": false,
            "index": 0,
            "isDiscardVisible": true,
            "isVisible": true,
            "label": "id",
            "fontStyle": "",
            "textColor": "",
            "columnType": "number",
            "horizontalAlignment": "LEFT",
            "isCellEditable": false,
            "width": 150,
            "enableFilter": true,
            "sticky": "",
            "originalId": "id",
            "cellBackground": "",
            "verticalAlignment": "CENTER"
        },
        "brand": {
            "computedValue": "{{Table1.processedTableData.map((currentRow, currentIndex) => ( currentRow[\"brand\"]))}}",
            "isEditable": false,
            "alias": "brand",
            "enableSort": true,
            "isSaveVisible": true,
            "id": "brand",
            "isDisabled": false,
            "allowSameOptionsInNewRow": true,
            "validation": {},
            "isCellVisible": true,
            "isDerived": false,
            "textSize": "0.875rem",
            "allowCellWrapping": false,
            "index": 1,
            "isDiscardVisible": true,
            "isVisible": true,
            "label": "brand",
            "fontStyle": "",
            "textColor": "",
            "columnType": "text",
            "horizontalAlignment": "LEFT",
            "isCellEditable": false,
            "width": 150,
            "enableFilter": true,
            "sticky": "",
            "originalId": "brand",
            "cellBackground": "",
            "verticalAlignment": "CENTER"
        }
    },
    "key": "c852mt7w8k",
    "canFreezeColumn": true,
    "isDeprecated": false,
    "rightColumn": 64,
    "textSize": "0.875rem",
    "widgetId": "rc33bx5sea",
    "allowAddNewRow": true,
    "minWidth": 450,
    "tableData": "",
    "label": "Data",
    "searchKey": "",
    "parentId": "0",
    "serverSidePaginationEnabled": true,
    "renderMode": "CANVAS",
    "mobileTopRow": 11,
    "horizontalAlignment": "LEFT",
    "isVisibleSearch": true,
    "responsiveBehavior": "fill",
    "mobileLeftColumn": 5,
    "isVisiblePagination": true,
    "verticalAlignment": "CENTER"
}